wasm/__init__.py
wasm/__main__.py
wasm/compat.py
wasm/decode.py
wasm/formatter.py
wasm/immtypes.py
wasm/modtypes.py
wasm/opcodes.py
wasm/types.py
wasm/wasmtypes.py
wasm-1.2.dist-info/LICENSE
wasm-1.2.dist-info/METADATA
wasm-1.2.dist-info/WHEEL
wasm-1.2.dist-info/entry_points.txt
wasm-1.2.dist-info/top_level.txt
wasm-1.2.dist-info/RECORD
